satisfy_calc/__init__.py
satisfy_calc/__main__.py
satisfy_calc/building.py
satisfy_calc/coproduct_recipes.py
satisfy_calc/fetch_item_names.py
satisfy_calc/fetch_recipes.py
satisfy_calc/item.py
satisfy_calc/recipe.py
satisfy_calc/recipe_storage.py
satisfy_calc/soup.py
satisfy_calc/tree.py
satisfy_calc-1.1.3.dist-info/LICENSE
satisfy_calc-1.1.3.dist-info/METADATA
satisfy_calc-1.1.3.dist-info/WHEEL
satisfy_calc-1.1.3.dist-info/entry_points.txt
satisfy_calc-1.1.3.dist-info/top_level.txt
satisfy_calc-1.1.3.dist-info/RECORD
