Metadata-Version: 2.1
Name: satisfy-calc
Version: 1.1.3
Summary: Command line crafting tree visualizer for Satisfactory Game by CoffeeStain Studios
Home-page: https://github.com/sedatDemiriz/satisfy-calc
Author: Sedat Demiriz
Author-email: sedatdemiriz97@gmail.com
License: MIT
Platform: UNKNOWN
Classifier: License :: OSI Approved :: MIT License
Classifier: Programming Language :: Python :: 3
Classifier: Programming Language :: Python :: 3.7
Requires-Dist: bs4
Requires-Dist: jsonpickle
Requires-Dist: requests
